schema_registry/__init__.py
schema_registry/client/__init__.py
schema_registry/client/client.py
schema_registry/client/errors.py
schema_registry/client/paths.py
schema_registry/client/schema.py
schema_registry/client/status.py
schema_registry/client/urls.py
schema_registry/client/utils.py
schema_registry/py.typed
schema_registry/serializers/__init__.py
schema_registry/serializers/errors.py
schema_registry/serializers/faust.py
schema_registry/serializers/message_serializer.py
python_schema_registry_client-2.6.1.dist-info/LICENSE
python_schema_registry_client-2.6.1.dist-info/METADATA
python_schema_registry_client-2.6.1.dist-info/WHEEL
python_schema_registry_client-2.6.1.dist-info/RECORD
