Metadata-Version: 2.3
Name: python-schema-registry-client
Version: 2.6.1
Summary: Python Rest Client to interact against Schema Registry confluent server
License: MIT
Author: Marcos Schroh
Author-email: schrohm@gmail.com
Requires-Python: >=3.8,<4.0
Classifier: Intended Audience :: Developers
Classifier: License :: OSI Approved :: MIT License
Classifier: Programming Language :: Python :: 3
Classifier: Programming Language :: Python :: 3.8
Classifier: Programming Language :: Python :: 3.9
Classifier: Programming Language :: Python :: 3.10
Classifier: Programming Language :: Python :: 3.11
Classifier: Programming Language :: Python :: 3.12
Classifier: Programming Language :: Python :: 3.13
Classifier: Programming Language :: Python :: 3 :: Only
Classifier: Topic :: Software Development
Provides-Extra: faust
Requires-Dist: anyio (>=2,<5)
Requires-Dist: fastavro (>=1.7.3,<2.0.0)
Requires-Dist: faust-streaming (>=0.10.11,<0.12.0) ; extra == "faust"
Requires-Dist: httpx (>=0.28,<0.29)
Requires-Dist: jsonschema (>=4.17.3,<5.0.0)
